CHANGES.rst
COPYING
COPYING.LESSER
MANIFEST.in
README.rst
setup.cfg
setup.py
tox.ini
./pyramid_walrus/__init__.py
./pyramid_walrus/backends.py
./pyramid_walrus/tests/__init__.py
./pyramid_walrus/tests/test_backends.py
pyramid_walrus.egg-info/PKG-INFO
pyramid_walrus.egg-info/SOURCES.txt
pyramid_walrus.egg-info/dependency_links.txt
pyramid_walrus.egg-info/requires.txt
pyramid_walrus.egg-info/top_level.txt
pyramid_walrus.egg-info/zip-safe